LICENSE
MANIFEST.in
README.md
setup.cfg
setup.py
PyFAT.egg-info/PKG-INFO
PyFAT.egg-info/SOURCES.txt
PyFAT.egg-info/dependency_links.txt
PyFAT.egg-info/requires.txt
PyFAT.egg-info/top_level.txt
example/fatigue_input.txt
example/monotonic_input.txt
example/fatigue/10-13.csv
example/fatigue/10-6.csv
example/fatigue/12-6.csv
example/fatigue/12-9.csv
example/fatigue/15-1.csv
example/fatigue/15-10.csv
example/fatigue/15-7.csv
example/fatigue/20-5.csv
example/fatigue/25-2.csv
example/fatigue/30-4.csv
example/fatigue/40-2.csv
example/fatigue/9-4.csv
example/monotonic/M-10-D.csv
example/monotonic/M-4-D.csv
example/monotonic/M-6-D.csv
example/monotonic/M-8-D.csv
pyfat/PyFAT.py
pyfat/__init__.py
pyfat/fatigue.py
pyfat/get_channels.py
pyfat/monotonic.py
pyfat/plots.py
pyfat/tests/__init__.py
pyfat/tests/test_PyFAT.py
pyfat/tests/test_fatigue.py
pyfat/tests/test_get_channels.py
pyfat/tests/test_monotonic.py
pyfat/tests/inputs/HL_Data_ex.csv
pyfat/tests/inputs/example_input.txt
pyfat/tests/inputs/fatigue_data_ex1.csv
pyfat/tests/inputs/fatigue_data_ex2.csv
pyfat/tests/inputs/mono_data_ex1.csv
pyfat/tests/inputs/mono_data_ex2.csv