Metadata-Version: 2.1
Name: PyFAT
Version: 0.0.2
Summary: This package analyzes .csv files created by material test systems to determine monotonic or fatigue material properties
Home-page: https://github.com/SoftwareDevEngResearch/PyFAT
Author: Kevan Gahan
Author-email: gahank@oregonstate.edu
License: MIT
Platform: UNKNOWN
Classifier: Programming Language :: Python :: 3
Classifier: License :: OSI Approved :: MIT License
Classifier: Operating System :: OS Independent
Requires-Python: >=3.6
